SANDI_python_toolbox/config/snakebids.yml
SANDI_python_toolbox/run.py
SANDI_python_toolbox/workflow/Snakefile
SANDI_python_toolbox/workflow/rules/analyze_all_datasets.smk
SANDI_python_toolbox/workflow/rules/process_all_datasets.smk
SANDI_python_toolbox/workflow/rules/train_machine_learning_model.smk
SANDI_python_toolbox/workflow/scripts/RiceMean.py
SANDI_python_toolbox/workflow/scripts/SphericalMeanFromSH.py
SANDI_python_toolbox/workflow/scripts/apply_MLP_python.py
SANDI_python_toolbox/workflow/scripts/apply_RF_python.py
SANDI_python_toolbox/workflow/scripts/build_training_set.py
SANDI_python_toolbox/workflow/scripts/drchrnd.py
SANDI_python_toolbox/workflow/scripts/llsFitSH.py
SANDI_python_toolbox/workflow/scripts/make_direction_average_SNR.py
SANDI_python_toolbox/workflow/scripts/make_direction_average_noisemap.py
SANDI_python_toolbox/workflow/scripts/my_murdaycotts.py
SANDI_python_toolbox/workflow/scripts/normalize_noisemap.py
SANDI_python_toolbox/workflow/scripts/run_model_fitting.py
SANDI_python_toolbox/workflow/scripts/setup_and_run_model_training.py
SANDI_python_toolbox/workflow/scripts/train_MLP_python.py
SANDI_python_toolbox/workflow/scripts/train_RF_python.py
sandi_python_toolbox-0.1.2.dist-info/METADATA
sandi_python_toolbox-0.1.2.dist-info/WHEEL
sandi_python_toolbox-0.1.2.dist-info/entry_points.txt
sandi_python_toolbox-0.1.2.dist-info/RECORD
