Metadata-Version: 2.1
Name: sandi-python-toolbox
Version: 0.1.2
Summary: SANDI model fitting in python + BIDS handling
License: BSD-2-Clause
Author: Bradley-Karat
Author-email: bkarat@uwo.ca
Requires-Python: >=3.7,<3.11
Classifier: License :: OSI Approved :: BSD License
Classifier: Programming Language :: Python :: 3
Classifier: Programming Language :: Python :: 3.7
Classifier: Programming Language :: Python :: 3.8
Classifier: Programming Language :: Python :: 3.9
Classifier: Programming Language :: Python :: 3.10
Requires-Dist: matplotlib (==3.4.2)
Requires-Dist: nibabel (==3.2.1)
Requires-Dist: numpy (==1.21.4)
Requires-Dist: scikit-image (==0.19.3)
Requires-Dist: scikit-learn (==1.0.2)
Requires-Dist: scipy (==1.7.3)
Requires-Dist: snakebids (==0.7.2)
Requires-Dist: snakemake (==7.25.0)
